{
  "forge_marker": 1,
  "defaults": {
    "model": "cube_all"
  },
  "variants": {
    "normal": [{}],
    "inventory": [
      {
        "transform": "forge:default-block"
      }
    ],
    "variant": {
      "brick": {
        "textures": {"all": "railcraft:blocks/brick_red_sandy_0"}
      },
      "fitted": {
        "textures": {"all": "railcraft:blocks/brick_red_sandy_1"}
      },
      "block": {
        "textures": {"all": "railcraft:blocks/brick_red_sandy_2"}
      },
      "ornate": {
        "textures": {"all": "railcraft:blocks/brick_red_sandy_3"}
      },
      "etched": {
        "textures": {"all": "railcraft:blocks/brick_red_sandy_4"}
      },
      "cobble": {
        "textures": {"all": "railcraft:blocks/brick_red_sandy_5"}
      }
    }
  }
}